SuRF-1.1.9.dist-info/DESCRIPTION.rst
SuRF-1.1.9.dist-info/METADATA
SuRF-1.1.9.dist-info/RECORD
SuRF-1.1.9.dist-info/WHEEL
SuRF-1.1.9.dist-info/metadata.json
SuRF-1.1.9.dist-info/top_level.txt
surf/__init__.py
surf/__version__.py
surf/exceptions.py
surf/log.py
surf/namespace.py
surf/noconflict.py
surf/rdf.py
surf/rest.py
surf/serializer.py
surf/session.py
surf/store.py
surf/util.py
surf/plugin/__init__.py
surf/plugin/manager.py
surf/plugin/query_reader.py
surf/plugin/reader.py
surf/plugin/writer.py
surf/plugin/rdflib/__init__.py
surf/plugin/rdflib/reader.py
surf/plugin/rdflib/writer.py
surf/plugin/sparql_protocol/__init__.py
surf/plugin/sparql_protocol/reader.py
surf/plugin/sparql_protocol/writer.py
surf/query/__init__.py
surf/query/update.py
surf/query/translator/__init__.py
surf/query/translator/sparql.py
surf/query/translator/sparul.py
surf/resource/__init__.py
surf/resource/lazy.py
surf/resource/result_proxy.py
