Metadata-Version: 2.0
Name: SuRF
Version: 1.1.9
Summary: Object RDF Mapper
Home-page: http://code.google.com/p/surfrdf/
Author: Cosmin Basca
Author-email: cosmin.basca at google.com
License: New BSD SOFTWARE
Download-URL: http://pypi.python.org/pypi/SuRF/
Keywords: Python SPARQL RDF resource mapper ORM query Semantic Web RDFS rdflib Object-Oriented
Platform: any
Classifier: Development Status :: 4 - Beta
Classifier: Intended Audience :: Developers
Classifier: License :: OSI Approved :: BSD License
Classifier: Operating System :: OS Independent
Classifier: Programming Language :: Python :: 2.6
Classifier: Programming Language :: Python :: 2.7
Classifier: Topic :: Software Development :: Libraries :: Python Modules
Requires-Dist: SPARQLWrapper (>=1.7.6)
Requires-Dist: rdflib (>=4.2.1)
